file_brain/__init__.py
file_brain/api/__init__.py
file_brain/api/models/__init__.py
file_brain/api/models/crawler.py
file_brain/api/models/file_event.py
file_brain/api/models/operations.py
file_brain/api/v1/__init__.py
file_brain/api/v1/endpoints/__init__.py
file_brain/api/v1/endpoints/config.py
file_brain/api/v1/endpoints/crawler.py
file_brain/api/v1/endpoints/files.py
file_brain/api/v1/endpoints/fs.py
file_brain/api/v1/endpoints/settings.py
file_brain/api/v1/endpoints/stats_extended.py
file_brain/api/v1/endpoints/system.py
file_brain/api/v1/endpoints/system_stream.py
file_brain/api/v1/endpoints/watch_paths.py
file_brain/api/v1/endpoints/wizard.py
file_brain/api/v1/router.py
file_brain/core/__init__.py
file_brain/core/app_info.py
file_brain/core/config.py
file_brain/core/exceptions.py
file_brain/core/factory.py
file_brain/core/frontend.py
file_brain/core/initialization.py
file_brain/core/logging.py
file_brain/core/paths.py
file_brain/core/telemetry.py
file_brain/core/typesense_schema.py
file_brain/database/__init__.py
file_brain/database/models/__init__.py
file_brain/database/models/base.py
file_brain/database/models/crawler_state.py
file_brain/database/models/setting.py
file_brain/database/models/watch_path.py
file_brain/database/models/wizard_state.py
file_brain/database/repositories/__init__.py
file_brain/database/repositories/base.py
file_brain/database/repositories/crawler_state.py
file_brain/database/repositories/settings.py
file_brain/database/repositories/watch_path.py
file_brain/database/repositories/wizard_state_repository.py
file_brain/docker-compose.yml
file_brain/frontend/__init__.py
file_brain/frontend/dist/assets/auto-CquwA8NN.js
file_brain/frontend/dist/assets/fa-brands-400-BfBXV7Mm.woff2
file_brain/frontend/dist/assets/fa-regular-400-BVHPE7da.woff2
file_brain/frontend/dist/assets/fa-solid-900-8GirhLYJ.woff2
file_brain/frontend/dist/assets/index-9udamLXJ.css
file_brain/frontend/dist/assets/index-QBAM67OI.js
file_brain/frontend/dist/icon.svg
file_brain-0.1.17.dist-info/METADATA
file_brain-0.1.17.dist-info/WHEEL
file_brain-0.1.17.dist-info/entry_points.txt
file_brain-0.1.17.dist-info/RECORD
