Metadata-Version: 2.4
Name: file-brain
Version: 0.1.17
Summary: Advanced file search engine powered by AI
License: GPL-3.0-or-later
Keywords: search,file-indexing,semantic-search,local-search,search-engine,gui,filesystem,fuzzy-search,file,artificial-intelligence,desktop-application,image-search,file-management,embedding,apache-tika,filesystem-indexer,document-search,typesense,archive-search,ocr
Author: Hamza Abbad
Author-email: contact@file-brain.com
Requires-Python: >=3.11,<3.15
Classifier: Development Status :: 4 - Beta
Classifier: Intended Audience :: End Users/Desktop
Classifier: License :: OSI Approved :: GNU General Public License v3 or later (GPLv3+)
Classifier: Programming Language :: Python :: 3.11
Classifier: Programming Language :: Python :: 3.12
Classifier: Programming Language :: Python :: 3.13
Classifier: Programming Language :: Python :: 3.14
Classifier: Topic :: Desktop Environment :: File Managers
Classifier: Topic :: Text Processing :: Indexing
Classifier: Environment :: GPU :: NVIDIA CUDA
Requires-Dist: aiohttp (>=3.13.2,<4.0.0)
Requires-Dist: chardet (>=5.2.0,<6.0.0)
Requires-Dist: docker (>=7.1.0,<8.0.0)
Requires-Dist: fastapi[standard-no-fastapi-cloud-cli] (>=0.121.0,<0.122.0)
Requires-Dist: huggingface-hub (>=1.2.4,<2.0.0)
Requires-Dist: platformdirs (>=4.5.1,<5.0.0)
Requires-Dist: podman (>=5.6.0,<6.0.0)
Requires-Dist: posthog (>=7.5.1,<8.0.0)
Requires-Dist: psutil (>=6.0.0,<7.0.0)
Requires-Dist: py-machineid (>=1.0.0,<2.0.0)
Requires-Dist: pydantic (>=2.12.4,<3.0.0)
Requires-Dist: pydantic-settings (>=2.11.0,<3.0.0)
Requires-Dist: python-magic (>=0.4.27,<0.5.0)
Requires-Dist: sqlalchemy (>=2.0.44,<3.0.0)
Requires-Dist: tika (>=3.1.0,<4.0.0)
Requires-Dist: typesense (>=1.1.1,<2.0.0)
Requires-Dist: watchdog (>=6.0.0,<7.0.0)
Project-URL: Homepage, https://file-brain.com
Project-URL: Issues, https://github.com/Hamza5/file-brain/issues
Project-URL: Repository, https://github.com/Hamza5/file-brain
